doxygen_snippets/__init__.py
doxygen_snippets/cache.py
doxygen_snippets/constants.py
doxygen_snippets/doxygen.py
doxygen_snippets/doxyrun.py
doxygen_snippets/finder.py
doxygen_snippets/generatorAuto.py
doxygen_snippets/generatorBase.py
doxygen_snippets/generatorSnippets.py
doxygen_snippets/markdown.py
doxygen_snippets/node.py
doxygen_snippets/plugin.py
doxygen_snippets/property.py
doxygen_snippets/runner.py
doxygen_snippets/utils.py
doxygen_snippets/xml_parser.py
doxygen_snippets/templates/__init__.py
doxygen_snippets/templates/annotated.py
doxygen_snippets/templates/classes.py
doxygen_snippets/templates/code.py
doxygen_snippets/templates/error.py
doxygen_snippets/templates/files.py
doxygen_snippets/templates/hierarchy.py
doxygen_snippets/templates/index.py
doxygen_snippets/templates/member.py
doxygen_snippets/templates/member_definition.py
doxygen_snippets/templates/member_table.py
doxygen_snippets/templates/modules.py
doxygen_snippets/templates/namespaces.py
doxygen_snippets/templates/page.py
doxygen_snippets/templates/pages.py
doxygen_snippets/templates/programlisting.py
mkdocs_doxygen_snippets_plugin-0.1.4.dist-info/LICENSE
mkdocs_doxygen_snippets_plugin-0.1.4.dist-info/METADATA
mkdocs_doxygen_snippets_plugin-0.1.4.dist-info/WHEEL
mkdocs_doxygen_snippets_plugin-0.1.4.dist-info/entry_points.txt
mkdocs_doxygen_snippets_plugin-0.1.4.dist-info/top_level.txt
mkdocs_doxygen_snippets_plugin-0.1.4.dist-info/RECORD
