Metadata-Version: 2.1
Name: mkdocs-doxygen-snippets-plugin
Version: 0.1.4
Summary: MkDocs Doxygen snippets plugin to create easy documentation
Home-page: https://github.com/JakubAndrysek/mkdocs-doxygen-snippets-plugin
Author: Jakub Andrýsek
Author-email: email@kubaandrysek.cz
License: MIT
Keywords: mkdocs
Platform: UNKNOWN
Classifier: License :: OSI Approved :: MIT License
Classifier: Programming Language :: Python :: 3.7
Classifier: Programming Language :: Python :: 3.8
Classifier: Programming Language :: Python :: 3.9
Classifier: Operating System :: OS Independent
Requires-Python: >=3.7
Requires-Dist: Jinja2
Requires-Dist: mkdocs
Requires-Dist: mkdocs (>=1.0.4)
Requires-Dist: ruamel.yaml
